m2x/__init__.py
m2x/api.py
m2x/client.py
m2x/utils.py
m2x/tests/__init__.py
m2x/tests/common.py
m2x/tests/test_api.py
m2x/tests/test_client.py
m2x/tests/test_utils.py
m2x/tests/v2/__init__.py
m2x/tests/v2/base.py
m2x/tests/v2/test_api.py
m2x/tests/v2/test_devices.py
m2x/tests/v2/test_distributions.py
m2x/tests/v2/test_keys.py
m2x/tests/v2/test_streams.py
m2x/v2/__init__.py
m2x/v2/api.py
m2x/v2/collections.py
m2x/v2/commands.py
m2x/v2/devices.py
m2x/v2/distributions.py
m2x/v2/jobs.py
m2x/v2/keys.py
m2x/v2/metadata.py
m2x/v2/resource.py
m2x/v2/streams.py
m2x-5.5.0.dist-info/DESCRIPTION.rst
m2x-5.5.0.dist-info/METADATA
m2x-5.5.0.dist-info/RECORD
m2x-5.5.0.dist-info/WHEEL
m2x-5.5.0.dist-info/metadata.json
m2x-5.5.0.dist-info/top_level.txt
