Metadata-Version: 2.0
Name: m2x
Version: 5.5.0
Summary: M2X Python API client
Home-page: https://github.com/attm2x/m2x-python
Author: Citrusbyte
Author-email: matias.aguirre@citrusbyte.com
License: MIT
Keywords: m2x,api
Platform: UNKNOWN
Classifier: Development Status :: 4 - Beta
Classifier: Topic :: Internet
Classifier: License :: OSI Approved :: MIT License
Classifier: Intended Audience :: Developers
Classifier: Programming Language :: Python
Classifier: Programming Language :: Python :: 2.7
Classifier: Programming Language :: Python :: 3
Classifier: Programming Language :: Python :: 3.3
Classifier: Programming Language :: Python :: 3.4
Classifier: Programming Language :: Python :: 3.5
Classifier: Programming Language :: Python :: 3.6
Requires-Dist: requests (>=2.0.1)
Requires-Dist: iso8601 (>=0.1.8)
